{
  "unit": 4,
  "lesson": 26,
  "title": "HSK 4 Vocabulary — Part 26",
  "cards": [
    {
      "type": "hanzi",
      "character": "可是",
      "romaji": "kě shì",
      "meaning": "but; however"
    },
    {
      "type": "hanzi",
      "character": "可惜",
      "romaji": "kě xī",
      "meaning": "it is a pity; what a pity; unfortunately"
    },
    {
      "type": "hanzi",
      "character": "肯定",
      "romaji": "kěn dìng",
      "meaning": "to be sure; to be certain; sure; certain; definite; to confirm; to affirm; affirmative; to approve; approval; recognition"
    },
    {
      "type": "hanzi",
      "character": "空气",
      "romaji": "kōng qì",
      "meaning": "air; atmosphere"
    },
    {
      "type": "hanzi",
      "character": "恐怕",
      "romaji": "kǒng pà",
      "meaning": "fear; to dread; I'm afraid that...; perhaps; maybe"
    },
    {
      "type": "hanzi",
      "character": "苦",
      "romaji": "kǔ",
      "meaning": "bitter; hardship; pain; to suffer; to bring suffering to; painstakingly"
    },
    {
      "type": "hanzi",
      "character": "宽",
      "romaji": "kuān",
      "meaning": "lenient; wide; broad"
    },
    {
      "type": "hanzi",
      "character": "困",
      "romaji": "kùn",
      "meaning": "sleepy; tired"
    },
    {
      "type": "hanzi",
      "character": "困难",
      "romaji": "kùn nan",
      "meaning": "difficult; challenging; straitened circumstances; difficult situation"
    },
    {
      "type": "hanzi",
      "character": "扩大",
      "romaji": "kuò dà",
      "meaning": "to expand; to enlarge; to broaden one's scope"
    }
  ]
}