{
  "unit": 4,
  "lesson": 52,
  "title": "HSK 4 Vocabulary — Part 52",
  "cards": [
    {
      "type": "hanzi",
      "character": "因此",
      "romaji": "yīn cǐ",
      "meaning": "thus; consequently; as a result"
    },
    {
      "type": "hanzi",
      "character": "引起",
      "romaji": "yǐn qǐ",
      "meaning": "to give rise to; to lead to; to cause; to arouse"
    },
    {
      "type": "hanzi",
      "character": "饮料",
      "romaji": "yǐn liào",
      "meaning": "drink; beverage"
    },
    {
      "type": "hanzi",
      "character": "印象",
      "romaji": "yìn xiàng",
      "meaning": "impression"
    },
    {
      "type": "hanzi",
      "character": "赢",
      "romaji": "yíng",
      "meaning": "to beat; to win; to profit"
    },
    {
      "type": "hanzi",
      "character": "硬",
      "romaji": "yìng",
      "meaning": "hard; stiff; strong; firm; resolutely; doggedly; good (quality); able (person)"
    },
    {
      "type": "hanzi",
      "character": "勇敢",
      "romaji": "yǒng gǎn",
      "meaning": "brave; courageous"
    },
    {
      "type": "hanzi",
      "character": "永远",
      "romaji": "yǒng yuǎn",
      "meaning": "forever; eternal"
    },
    {
      "type": "hanzi",
      "character": "优点",
      "romaji": "yōu diǎn",
      "meaning": "merit; benefit; strong point; advantage; CL:個|个[gè]"
    },
    {
      "type": "hanzi",
      "character": "优秀",
      "romaji": "yōu xiù",
      "meaning": "outstanding; excellent"
    }
  ]
}