{
  "unit": 5,
  "lesson": 17,
  "title": "HSK 5 Vocabulary — Part 17",
  "cards": [
    {
      "type": "hanzi",
      "character": "从而",
      "romaji": "cóng ér",
      "meaning": "thus; thereby"
    },
    {
      "type": "hanzi",
      "character": "从前",
      "romaji": "cóng qián",
      "meaning": "previously; formerly; once upon a time"
    },
    {
      "type": "hanzi",
      "character": "从事",
      "romaji": "cóng shì",
      "meaning": "to go for; to engage in; to undertake; to deal with; to handle; to do"
    },
    {
      "type": "hanzi",
      "character": "醋",
      "romaji": "cù",
      "meaning": "vinegar"
    },
    {
      "type": "hanzi",
      "character": "促进",
      "romaji": "cù jìn",
      "meaning": "to promote (an idea or cause); to advance; boost"
    },
    {
      "type": "hanzi",
      "character": "促使",
      "romaji": "cù shǐ",
      "meaning": "to induce; to promote; to urge; to impel; to bring about; to provoke; to drive (sb to do sth); to catalyze; to actuate; to contribute to (some development)"
    },
    {
      "type": "hanzi",
      "character": "催",
      "romaji": "cuī",
      "meaning": "to urge; to press; to prompt; to rush sb; to hasten sth; to expedite"
    },
    {
      "type": "hanzi",
      "character": "存",
      "romaji": "cún",
      "meaning": "to exist; to deposit; to store; to keep; to survive"
    },
    {
      "type": "hanzi",
      "character": "存在",
      "romaji": "cún zài",
      "meaning": "to exist; to be; existence"
    },
    {
      "type": "hanzi",
      "character": "错误",
      "romaji": "cuò wù",
      "meaning": "error; mistake; CL:個|个[gè]; mistaken; false; wrong"
    }
  ]
}