{
  "unit": 6,
  "lesson": 122,
  "title": "HSK 6 Vocabulary — Part 122",
  "cards": [
    {
      "type": "hanzi",
      "character": "落成",
      "romaji": "luò chéng",
      "meaning": "to complete a construction project"
    },
    {
      "type": "hanzi",
      "character": "落实",
      "romaji": "luò shí",
      "meaning": "practical; workable; to implement; to carry out; to decide"
    },
    {
      "type": "hanzi",
      "character": "络绎不绝",
      "romaji": "luò yì bù jué",
      "meaning": "continuously; in an endless stream (idiom)"
    },
    {
      "type": "hanzi",
      "character": "屡次",
      "romaji": "lǚ cì",
      "meaning": "repeatedly; time and again"
    },
    {
      "type": "hanzi",
      "character": "履行",
      "romaji": "lǚ xíng",
      "meaning": "to fulfill (one's obligations); to carry out (a task); to implement (an agreement); to perform"
    },
    {
      "type": "hanzi",
      "character": "掠夺",
      "romaji": "lvè duó",
      "meaning": "to plunder; to rob; also written 略奪|略夺"
    },
    {
      "type": "hanzi",
      "character": "略微",
      "romaji": "lvè wēi",
      "meaning": "a little bit; slightly"
    },
    {
      "type": "hanzi",
      "character": "麻痹",
      "romaji": "má bì",
      "meaning": "paralysis; palsy; numbness; to benumb"
    },
    {
      "type": "hanzi",
      "character": "麻木",
      "romaji": "má mù",
      "meaning": "numb; insensitive; apathetic"
    },
    {
      "type": "hanzi",
      "character": "麻醉",
      "romaji": "má zuì",
      "meaning": "anesthesia; fig. to poison (sb's mind)"
    }
  ]
}