{
  "unit": 3,
  "lesson": 9,
  "title": "HSK 3 Vocabulary — Part 9",
  "cards": [
    {
      "type": "hanzi",
      "character": "跟",
      "romaji": "gēn",
      "meaning": "heel; to follow closely; to go with; to marry sb (of woman); with; towards; as (compared to); from (different from); and (in addition to)"
    },
    {
      "type": "hanzi",
      "character": "更",
      "romaji": "gèng",
      "meaning": "more; even more; further; still; still more"
    },
    {
      "type": "hanzi",
      "character": "公园",
      "romaji": "gōng yuán",
      "meaning": "public park; CL:場|场[chǎng]"
    },
    {
      "type": "hanzi",
      "character": "故事",
      "romaji": "gù shi",
      "meaning": "narrative; story; tale"
    },
    {
      "type": "hanzi",
      "character": "刮",
      "romaji": "guā",
      "meaning": "to blow (of the wind)"
    },
    {
      "type": "hanzi",
      "character": "关",
      "romaji": "guān",
      "meaning": "mountain pass; to close; to shut; to turn off; to concern; to involve"
    },
    {
      "type": "hanzi",
      "character": "关系",
      "romaji": "guān xì",
      "meaning": "variant of 關係|关系[guān xì]"
    },
    {
      "type": "hanzi",
      "character": "关心",
      "romaji": "guān xīn",
      "meaning": "to care for sth; caring; concerned"
    },
    {
      "type": "hanzi",
      "character": "关于",
      "romaji": "guān yú",
      "meaning": "pertaining to; concerning; regarding; with regards to; about; a matter of"
    },
    {
      "type": "hanzi",
      "character": "国家",
      "romaji": "guó jiā",
      "meaning": "country; nation; state; CL:個|个[gè]"
    }
  ]
}